evilblade/__init__.py
evilblade/a.py
evilblade_user/__init__.py
evilblade-1.1.7.91.dist-info/METADATA
evilblade-1.1.7.91.dist-info/WHEEL
evilblade-1.1.7.91.dist-info/top_level.txt
evilblade-1.1.7.91.dist-info/RECORD
