Metadata-Version: 2.2
Name: evilblade
Version: 1.1.7.91
Summary: 7 N1nEmAn's evilblade!!
Requires-Dist: pwntools
Requires-Dist: LibcSearcher
Dynamic: description
Dynamic: description-content-type
Dynamic: requires-dist
Dynamic: summary
